collective.tiles.discussion-1.0.0a1-py3.11-nspkg.pth
collective/tiles/discussion/__init__.py
collective/tiles/discussion/configure.zcml
collective/tiles/discussion/discussion_tile.pt
collective/tiles/discussion/interfaces.py
collective/tiles/discussion/messagefactory.py
collective/tiles/discussion/permissions.zcml
collective/tiles/discussion/profiles.zcml
collective/tiles/discussion/setuphandlers.py
collective/tiles/discussion/testing.py
collective/tiles/discussion/tile.py
collective/tiles/discussion/vocabulary.py
collective/tiles/discussion/locales/collective.tiles.discussion.pot
collective/tiles/discussion/locales/update.sh
collective/tiles/discussion/locales/it/LC_MESSAGES/collective.tiles.discussion.mo
collective/tiles/discussion/locales/it/LC_MESSAGES/collective.tiles.discussion.po
collective/tiles/discussion/locales/nl/LC_MESSAGES/collective.tiles.discussion.mo
collective/tiles/discussion/locales/nl/LC_MESSAGES/collective.tiles.discussion.po
collective/tiles/discussion/profiles/default/browserlayer.xml
collective/tiles/discussion/profiles/default/metadata.xml
collective/tiles/discussion/profiles/default/rolemap.xml
collective/tiles/discussion/profiles/default/registry/main.xml
collective/tiles/discussion/profiles/uninstall/browserlayer.xml
collective/tiles/discussion/profiles/uninstall/registry/main.xml
collective/tiles/discussion/tests/__init__.py
collective/tiles/discussion/tests/test_setup.py
collective.tiles.discussion-1.0.0a1.dist-info/LICENSE.GPL
collective.tiles.discussion-1.0.0a1.dist-info/LICENSE.rst
collective.tiles.discussion-1.0.0a1.dist-info/METADATA
collective.tiles.discussion-1.0.0a1.dist-info/WHEEL
collective.tiles.discussion-1.0.0a1.dist-info/entry_points.txt
collective.tiles.discussion-1.0.0a1.dist-info/namespace_packages.txt
collective.tiles.discussion-1.0.0a1.dist-info/top_level.txt
collective.tiles.discussion-1.0.0a1.dist-info/RECORD
