Metadata-Version: 2.1
Name: collective.tiles.discussion
Version: 1.0.0a1
Summary: Tile for showing most recent discussion items.
Home-page: https://github.com/collective/collective.tiles.discussion
Author: Maurits van Rees
Author-email: maurits@vanrees.org
License: GPL version 2
Project-URL: PyPI, https://pypi.org/project/collective.tiles.discussion/
Project-URL: Source, https://github.com/collective/collective.tiles.discussion
Project-URL: Tracker, https://github.com/collective/collective.tiles.discussion/issues
Keywords: Python Plone CMS
Classifier: Development Status :: 3 - Alpha
Classifier: Environment :: Web Environment
Classifier: Framework :: Plone
Classifier: Framework :: Plone :: Addon
Classifier: Framework :: Plone :: 6.0
Classifier: Programming Language :: Python
Classifier: Programming Language :: Python :: 3.8
Classifier: Programming Language :: Python :: 3.9
Classifier: Programming Language :: Python :: 3.10
Classifier: Programming Language :: Python :: 3.11
Classifier: Operating System :: OS Independent
Classifier: License :: OSI Approved :: GNU General Public License v2 (GPLv2)
Requires-Python: >=3.8
License-File: LICENSE.GPL
License-File: LICENSE.rst
Requires-Dist: setuptools
Requires-Dist: plone.app.tiles
Provides-Extra: test
Requires-Dist: plone.app.mosaic ; extra == 'test'
Requires-Dist: plone.app.testing ; extra == 'test'
Requires-Dist: plone.testing ; extra == 'test'
